simple_http_server_jinja/__init__.py
simple_http_server_jinja-0.1.1.dist-info/LICENSE
simple_http_server_jinja-0.1.1.dist-info/METADATA
simple_http_server_jinja-0.1.1.dist-info/WHEEL
simple_http_server_jinja-0.1.1.dist-info/top_level.txt
simple_http_server_jinja-0.1.1.dist-info/RECORD
