Metadata-Version: 2.1
Name: simple_http_server_jinja
Version: 0.1.1
Summary: This is a simple http server, use MVC like design.
Author-email: keijack <keijack.wu@gmail.com>
License: MIT License
Project-URL: homepage, https://github.com/keijack/python-simple-http-server-jinja
Project-URL: repository, https://github.com/keijack/python-simple-http-server-jinja
Keywords: http-server,jinja,http,web,web-server
Classifier: Programming Language :: Python :: 3
Classifier: License :: OSI Approved :: MIT License
Classifier: Operating System :: OS Independent
Requires-Python: >=3.7
License-File: LICENSE
Requires-Dist: simple-http-server >=0.14
Requires-Dist: jinja2 >=3.1
